pypika/__init__.py
pypika/analytics.py
pypika/dialects.py
pypika/enums.py
pypika/functions.py
pypika/pseudocolumns.py
pypika/queries.py
pypika/terms.py
pypika/utils.py
pypika/clickhouse/__init__.py
pypika/clickhouse/array.py
pypika/clickhouse/condition.py
pypika/clickhouse/dates_and_times.py
pypika/clickhouse/nullable_arg.py
pypika/clickhouse/search_string.py
pypika/clickhouse/type_conversion.py
PyPika_git-0.50.0.dist-info/LICENSE.txt
PyPika_git-0.50.0.dist-info/METADATA
PyPika_git-0.50.0.dist-info/WHEEL
PyPika_git-0.50.0.dist-info/top_level.txt
PyPika_git-0.50.0.dist-info/RECORD
