Metadata-Version: 2.1
Name: PyPika-git
Version: 0.50.0
Summary: A SQL query builder API for Python
Home-page: https://github.com/jaalzateolaya/pypika
Author: Alexander Alzate
Author-email: it@jaalzateolaya.com
License: Apache License Version 2.0
Keywords: pypika python query builder querybuilder sql mysql postgres psql oracle vertica aggregated relational database rdbms business analytics bi data science analysis pandas orm object mapper
Classifier: License :: OSI Approved :: Apache Software License
Classifier: Development Status :: 5 - Production/Stable
Classifier: Intended Audience :: Developers
Classifier: Programming Language :: Python :: 3
Classifier: Programming Language :: PL/SQL
Classifier: Topic :: Software Development :: Libraries :: Python Modules
Classifier: Topic :: Scientific/Engineering :: Information Analysis
Classifier: Topic :: Scientific/Engineering :: Mathematics
Classifier: Operating System :: POSIX
Classifier: Operating System :: MacOS :: MacOS X
Classifier: Operating System :: Microsoft :: Windows
License-File: LICENSE.txt
